MANIFEST.in
README
setup.py
django_timezones.egg-info/PKG-INFO
django_timezones.egg-info/SOURCES.txt
django_timezones.egg-info/dependency_links.txt
django_timezones.egg-info/requires.txt
django_timezones.egg-info/top_level.txt
docs/how_to_use.txt
docs/index.txt
timezones/__init__.py
timezones/decorators.py
timezones/fields.py
timezones/forms.py
timezones/models.py
timezones/tests.py
timezones/utils.py
timezones/templatetags/__init__.py
timezones/templatetags/timezone_filters.py