Metadata-Version: 1.0
Name: django-timezones
Version: 0.1.0
Summary: A Django reusable app to deal with timezone localization for users
Home-page: http://code.google.com/p/django-timezones/
Author: Brian Rosner
Author-email: brosner@gmail.com
License: BSD
Platform: UNKNOWN
Classifier: Development Status :: 4 - Beta
Classifier: Environment :: Web Environment
Classifier: Intended Audience :: Developers
Classifier: License :: OSI Approved :: BSD License
Classifier: Operating System :: OS Independent
Classifier: Programming Language :: Python
Classifier: Topic :: Utilities
Classifier: Framework :: Django
